dash_router/__init__.py
dash_router/_validation.py
dash_router/components.py
dash_router/core/__init__.py
dash_router/core/context.py
dash_router/core/execution.py
dash_router/core/query_params.py
dash_router/core/routing.py
dash_router/router.py
dash_router/utils/constants.py
dash_router/utils/helper_functions.py
flash_router/__init__.py
flash_router/_validation.py
flash_router/components.py
flash_router/core/__init__.py
flash_router/core/context.py
flash_router/core/execution.py
flash_router/core/query_params.py
flash_router/core/routing.py
flash_router/router.py
flash_router/utils/constants.py
flash_router/utils/helper_functions.py
flash_router-0.5.0b5.dist-info/LICENSE
flash_router-0.5.0b5.dist-info/METADATA
flash_router-0.5.0b5.dist-info/WHEEL
flash_router-0.5.0b5.dist-info/RECORD
