Metadata-Version: 2.3
Name: flash_router
Version: 0.5.0b5
Summary: File-system based router for Dash and Flash applications.
License: MIT
Author: chgiesse
Requires-Python: >=3.12,<4.0
Classifier: License :: OSI Approved :: MIT License
Classifier: Programming Language :: Python :: 3
Classifier: Programming Language :: Python :: 3.12
Classifier: Programming Language :: Python :: 3.13
Provides-Extra: async
Requires-Dist: dash (>=3.0.0rc1,<4.0.0)
Requires-Dist: dash-flash (>=1.0.0,<2.0.0) ; extra == "async"
Requires-Dist: pydantic (>=2.10.4,<3.0.0)
Project-URL: Repository, https://github.com/chgiesse/dash-router
